[
  {
    "id": "entrance_exit_gate",
    "kind": "gate",
    "name": "Front Gate",
    "tags": [
      "enter",
      "leave",
      "start",
      "begin",
      "entrance",
      "exit"
    ]
  },
  {
    "id": "fountain",
    "kind": "intersection",
    "name": "Fountain",
    "tags": []
  },
  {
    "id": "hollywood_backlot",
    "kind": "exhibit",
    "name": "Hollywood Backlot Stage",
    "tags": [
      "hollywood",
      "stage"
    ]
  },
  {
    "id": "hyperion",
    "kind": "exhibit",
    "name": "Frozen Hyperion",
    "tags": [
      "hollywood",
      "stage"
    ]
  },
  {
    "id": "soarin_junction",
    "kind": "intersection",
    "name": "Soarin Junction",
    "tags": [

    ]
  },
  {
    "id": "grizzly_run",
    "kind": "exhibit",
    "name": "Grizzly River Run",
    "tags": [
      "woods",
      "water"
    ]
  },
  {
    "id": "hotel",
    "kind": "exhibit",
    "name": "Hotel",
    "tags": [
      "hotel"
    ]
  },
  {
    "id": "hollywood_hotel",
    "kind": "exhibit",
    "name": "Hollywood Hotel",
    "tags": [
      "hollywood",
      "horror",
      "tall"
    ]
  },
  {
    "id": "bugs_land",
    "kind": "intersection",
    "name": "Bug's Land Junction",
    "tags": [
      "lame",
      "place_to_sit"
    ]
  },
  {
    "id": "junkyard_jamboree",
    "kind": "exhibit",
    "name": "Junkyard Jamboree",
    "tags": [
      "cars",
      "carsland"
    ]
  },
  {
    "id": "chew_chew",
    "kind": "exhibit",
    "name": "Chew Chew Train",
    "tags": [
      "lame"
    ]
  }
]